[
    {
      "image": "assets/images/product1.png",
      "name": "Vợt cầu lông Yonex",
      "price": 1500000
    },
    {
      "image": "assets/images/product5.png",
      "name": "Giày cầu lông Adidas",
      "price": 1200000
    },
    {
        "image": "assets/images/product3.png",
        "name": "Giày cầu lông Adidas",
        "price": 1200000
      },
      {
        "image": "assets/images/product4.png",
        "name": "Giày cầu lông Adidas",
        "price": 1200000
      },
      {
        "image": "assets/images/product5.png",
        "name": "Giày cầu lông Adidas",
        "price": 1200000
      },
      {
        "image": "assets/images/product6.png",
        "name": "Giày cầu lông Adidas",
        "price": 1200000
      },
      {
        "image": "assets/images/product3.png",
        "name": "Giày cầu lông Adidas",
        "price": 1200000
      },
      {
        "image": "assets/images/product6.png",
        "name": "Giày cầu lông Adidas",
        "price": 1200000
      },
      {
        "image": "assets/images/product3.png",
        "name": "Giày cầu lông Adidas",
        "price": 1200000
      },
      {
        "image": "assets/images/product1.png",
        "name": "Giày cầu lông Adidas",
        "price": 1200000
      },
      {
        "image": "assets/images/product6.png",
        "name": "Giày cầu lông Adidas",
        "price": 1200000
      },
      {
        "image": "assets/images/product1.png",
        "name": "Giày cầu lông Adidas",
        "price": 1200000
      },
      {
        "image": "assets/images/product4.png",
        "name": "Giày cầu lông Adidas",
        "price": 1200000
      },
      {
        "image": "assets/images/product3.png",
        "name": "Giày cầu lông Adidas",
        "price": 1200000
      },
      {
        "image": "assets/images/product4.png",
        "name": "Giày cầu lông Adidas",
        "price": 1200000
      },
      {
        "image": "assets/images/product6.png",
        "name": "Giày cầu lông Adidas",
        "price": 1200000
      },
      {
        "image": "assets/images/product3.png",
        "name": "Giày cầu lông Adidas",
        "price": 1200000
      },
      {
        "image": "assets/images/product5.png",
        "name": "Giày cầu lông Adidas",
        "price": 1200000
      },
      {
        "image": "assets/images/product1.png",
        "name": "Giày cầu lông Adidas",
        "price": 1200000
      },
    {
      "image": "assets/images/product3.png",
      "name": "Quả cầu lông Victor",
      "price": 200000
    }
    
  ]